any_registries/__init__.py
any_registries/exceptions.py
any_registries/py.typed
any_registries-0.3.0.dist-info/licenses/LICENSE
any_registries-0.3.0.dist-info/METADATA
any_registries-0.3.0.dist-info/WHEEL
any_registries-0.3.0.dist-info/top_level.txt
any_registries-0.3.0.dist-info/RECORD
