Metadata-Version: 2.4
Name: any-registries
Version: 0.3.0
Summary: A flexible registry system for Python applications with auto-loading capabilities
Author-email: Starscribers <Starscribers@gmail.com>
Project-URL: Homepage, https://github.com/Starscribers/python-packages
Project-URL: Repository, https://github.com/Starscribers/python-packages.git
Project-URL: Issues, https://github.com/Starscribers/python-packages/issues
Project-URL: Documentation, https://github.com/Starscribers/python-packages/blob/main/any-registries/README.md
Classifier: Development Status :: 4 - Beta
Classifier: Intended Audience :: Developers
Classifier: License :: OSI Approved :: MIT License
Classifier: Operating System :: OS Independent
Classifier: Programming Language :: Python
Classifier: Programming Language :: Python :: 3
Classifier: Programming Language :: Python :: 3.8
Classifier: Programming Language :: Python :: 3.9
Classifier: Programming Language :: Python :: 3.10
Classifier: Programming Language :: Python :: 3.11
Classifier: Programming Language :: Python :: 3.12
Classifier: Topic :: Software Development :: Libraries :: Python Modules
Classifier: Topic :: Utilities
Classifier: Typing :: Typed
Requires-Python: >=3.9
License-File: LICENSE
Requires-Dist: typing_extensions>=4.0.0
Provides-Extra: dev
Requires-Dist: pytest>=7.0.0; extra == "dev"
Requires-Dist: black>=22.0.0; extra == "dev"
Requires-Dist: isort>=5.10.0; extra == "dev"
Requires-Dist: mypy>=0.950; extra == "dev"
Requires-Dist: flake8>=4.0.0; extra == "dev"
Requires-Dist: pre-commit>=3.0.0; extra == "dev"
Requires-Dist: bandit>=1.7.0; extra == "dev"
Requires-Dist: twine>=4.0.0; extra == "dev"
Requires-Dist: types-setuptools>=68.0.0; extra == "dev"
Provides-Extra: testing
Requires-Dist: pytest>=7.0.0; extra == "testing"
Requires-Dist: pytest-cov>=3.0.0; extra == "testing"
Dynamic: license-file
